pymjc/__init__.py
pymjc/_mjc.py
pymjc/_mjc.pyi
pymjc-1.0.3.dist-info/METADATA
pymjc-1.0.3.dist-info/WHEEL
pymjc-1.0.3.dist-info/licenses/LICENSE
pymjc-1.0.3.dist-info/RECORD
