Metadata-Version: 2.1
Name: pymjc
Version: 1.0.3
Summary: Minimum Jump Cost dissimilarity measure in Python
Project-URL: Homepage, https://github.com/nup002/pymjc
Project-URL: Bug Tracker, https://github.com/nup002/pymjc/issues
Author-email: Magne Eik Lauritzen <mag.lauritzen@gmail.com>
License: MIT License
License-File: LICENSE
Keywords: data science,dissimilarity measure
Classifier: Intended Audience :: Science/Research
Classifier: License :: OSI Approved :: MIT License
Classifier: Operating System :: OS Independent
Classifier: Programming Language :: Python :: 3
Requires-Python: >=3.7
Requires-Dist: matplotlib>=3.4
Requires-Dist: numpy>=1.20.0
